{"version": "https://jsonfeed.org/version/1.1", "title": "Denverite: Denver News", "home_page_url": "https://sreynen.github.io/denver-news/", "feed_url": "https://sreynen.github.io/denver-news/denverite.json", "items": [{"id": "https://www.denverpost.com/2021/09/14/aurora-marijuana-hospitality-ordinance/", "url": "https://www.denverpost.com/2021/09/14/aurora-marijuana-hospitality-ordinance/", "title": "Aurora reverses itself on pot hospitality measure when second vote comes up short", "date_published": "2021-09-14T22:22:50+00:00", "date_modified": "2021-09-14T16:23:39+00:00"}, {"id": "https://www.denverpost.com/2021/09/14/joe-biden-colorado-visit-climate-energy-infrastructure/", "url": "https://www.denverpost.com/2021/09/14/joe-biden-colorado-visit-climate-energy-infrastructure/", "title": "Joe Biden in Colorado: \u201cWe have to make changes to slow climate change now\u201d", "date_published": "2021-09-14T22:03:09+00:00", "date_modified": "2021-09-14T16:12:40+00:00"}, {"id": "https://www.denverpost.com/2021/09/14/colorado-stubhub-refunds/", "url": "https://www.denverpost.com/2021/09/14/colorado-stubhub-refunds/", "title": "StubHub to refund over $3 million to more than 8,500 Colorado customers", "date_published": "2021-09-14T21:57:16+00:00", "date_modified": "2021-09-14T16:16:33+00:00"}, {"id": "https://www.denverpost.com/2021/09/14/watch-president-joe-biden-visits-national-renewable-energy-laboratory-in-colorado/", "url": "https://www.denverpost.com/2021/09/14/watch-president-joe-biden-visits-national-renewable-energy-laboratory-in-colorado/", "title": "WATCH: President Joe Biden visits National Renewable Energy Laboratory in Colorado", "date_published": "2021-09-14T21:29:49+00:00", "date_modified": "2021-09-14T15:29:49+00:00"}, {"id": "https://www.denverpost.com/2021/09/14/denver-kkk-members-map-database/", "url": "https://www.denverpost.com/2021/09/14/denver-kkk-members-map-database/", "title": "See where 1920s Denver Ku Klux Klan members lived, search the database", "date_published": "2021-09-14T21:19:28+00:00", "date_modified": "2021-09-14T15:20:51+00:00"}, {"id": "https://www.denverpost.com/2021/09/14/shannon-kent-lake-county-coroner-guilty/", "url": "https://www.denverpost.com/2021/09/14/shannon-kent-lake-county-coroner-guilty/", "title": "Former Lake County coroner Shannon Kent found guilty of official misconduct", "date_published": "2021-09-14T20:59:28+00:00", "date_modified": "2021-09-14T15:25:11+00:00"}, {"id": "https://www.denverpost.com/2021/09/14/sept-11-van-ride-omaha-denver-joyce-blutt/", "url": "https://www.denverpost.com/2021/09/14/sept-11-van-ride-omaha-denver-joyce-blutt/", "title": "\u201cA guardian angel\u201d: Colorado woman comes forward in daughter\u2019s quest to find 7 strangers her father helped on 9/11", "date_published": "2021-09-14T20:23:57+00:00", "date_modified": "2021-09-14T14:23:57+00:00"}, {"id": "https://www.denverpost.com/2021/09/14/kkk-denver-map/", "url": "https://www.denverpost.com/2021/09/14/kkk-denver-map/", "title": "\u201cThey were just everywhere\u201d: Map of Denver Ku Klux Klan addresses in 1920s shows members in every corner of city", "date_published": "2021-09-14T20:00:39+00:00", "date_modified": "2021-09-14T13:40:53+00:00"}, {"id": "https://www.denverpost.com/2021/09/14/colorado-wildfires-black-mountain-fire-morgan-creek/", "url": "https://www.denverpost.com/2021/09/14/colorado-wildfires-black-mountain-fire-morgan-creek/", "title": "Colorado wildfires: Black Mountain Fire nears full containment; other blazes stay quiet", "date_published": "2021-09-14T14:59:05+00:00", "date_modified": "2021-09-14T08:59:05+00:00"}, {"id": "https://www.denverpost.com/2021/09/14/denver-weather-tuesday-cool-rain/", "url": "https://www.denverpost.com/2021/09/14/denver-weather-tuesday-cool-rain/", "title": "Denver weather: Cooler with a chance of storms Tuesday", "date_published": "2021-09-14T13:08:26+00:00", "date_modified": "2021-09-14T07:08:26+00:00"}, {"id": "https://www.denverpost.com/2021/09/14/small-mountain-towns-colorado/", "url": "https://www.denverpost.com/2021/09/14/small-mountain-towns-colorado/", "title": "To see fall colors, skip the tourist traps and head to these small Colorado towns instead", "date_published": "2021-09-14T12:00:26+00:00", "date_modified": "2021-09-13T16:15:12+00:00"}, {"id": "https://www.denverpost.com/2021/09/14/colorado-biden-solar-energy-renewables/", "url": "https://www.denverpost.com/2021/09/14/colorado-biden-solar-energy-renewables/", "title": "Colorado looks to be ahead of Biden\u2019s called-for pace on renewable energy", "date_published": "2021-09-14T12:00:16+00:00", "date_modified": "2021-09-13T19:43:18+00:00"}, {"id": "https://www.denverpost.com/2021/09/14/lola-coastal-mexican-closed-denver-lohi/", "url": "https://www.denverpost.com/2021/09/14/lola-coastal-mexican-closed-denver-lohi/", "title": "Lola Coastal Mexican closes after 15 years on prominent LoHi corner", "date_published": "2021-09-14T12:00:01+00:00", "date_modified": "2021-09-13T15:45:53+00:00"}, {"id": "https://www.denverpost.com/2021/09/13/denver-protester-lawsuit/", "url": "https://www.denverpost.com/2021/09/13/denver-protester-lawsuit/", "title": "50 demonstrators sue Denver alleging police illegally injured or arrested them during 2020 protests", "date_published": "2021-09-14T01:01:25+00:00", "date_modified": "2021-09-13T19:11:02+00:00"}, {"id": "https://www.denverpost.com/2021/09/13/bob-enyart-dies-covid-19/", "url": "https://www.denverpost.com/2021/09/13/bob-enyart-dies-covid-19/", "title": "Bob Enyart, conservative firebrand and pastor, dies of COVID-19", "date_published": "2021-09-14T00:14:08+00:00", "date_modified": "2021-09-13T18:14:08+00:00"}, {"id": "https://www.denverpost.com/2021/09/13/charges-dropped-aurora-protest-leaders/", "url": "https://www.denverpost.com/2021/09/13/charges-dropped-aurora-protest-leaders/", "title": "Remaining charges dropped against Aurora protest leaders", "date_published": "2021-09-13T23:05:30+00:00", "date_modified": "2021-09-13T17:12:46+00:00"}, {"id": "https://www.denverpost.com/2021/09/13/colorado-covid-booster-shots-nursing-homes/", "url": "https://www.denverpost.com/2021/09/13/colorado-covid-booster-shots-nursing-homes/", "title": "Colorado ready to offer COVID boosters in nursing homes starting next week \u2014 if feds sign off", "date_published": "2021-09-13T21:44:33+00:00", "date_modified": "2021-09-13T15:48:45+00:00"}, {"id": "https://www.denverpost.com/2021/09/13/denver-extends-contract-of-hazmat-cleanup-company-involved-in-unhoused-sweeps/", "url": "https://www.denverpost.com/2021/09/13/denver-extends-contract-of-hazmat-cleanup-company-involved-in-unhoused-sweeps/", "title": "Denver extends contract of hazmat cleanup company involved in unhoused sweeps", "date_published": "2021-09-13T21:33:27+00:00", "date_modified": "2021-09-13T21:09:00+00:00"}, {"id": "https://www.denverpost.com/2021/09/13/joe-biden-colorado-climate-change/", "url": "https://www.denverpost.com/2021/09/13/joe-biden-colorado-climate-change/", "title": "Joe Biden to visit National Renewable Energy Laboratory on Tuesday", "date_published": "2021-09-13T20:35:31+00:00", "date_modified": "2021-09-13T14:36:04+00:00"}, {"id": "https://www.denverpost.com/2021/09/13/colorado-redistricting-statehouse-democrats/", "url": "https://www.denverpost.com/2021/09/13/colorado-redistricting-statehouse-democrats/", "title": "Democrats would hold edge at Colorado statehouse under latest redistricting map", "date_published": "2021-09-13T20:04:57+00:00", "date_modified": "2021-09-13T14:05:40+00:00"}, {"id": "https://www.denverpost.com/2021/09/13/pandemic-events-activities-safety-vaccine-covid-colorado/", "url": "https://www.denverpost.com/2021/09/13/pandemic-events-activities-safety-vaccine-covid-colorado/", "title": "How are you deciding which activities are safe during this stage of the pandemic? The Denver Post wants to know", "date_published": "2021-09-13T19:31:44+00:00", "date_modified": "2021-09-13T13:31:44+00:00"}, {"id": "https://www.denverpost.com/2021/09/13/factotum-brewhouse-denver-closing/", "url": "https://www.denverpost.com/2021/09/13/factotum-brewhouse-denver-closing/", "title": "A Sunnyside brewery will close due to a rent dispute with its landlord", "date_published": "2021-09-13T17:02:29+00:00", "date_modified": "2021-09-13T11:02:29+00:00"}, {"id": "https://www.denverpost.com/2021/09/13/interstate-70-land-closure-silver-plume/", "url": "https://www.denverpost.com/2021/09/13/interstate-70-land-closure-silver-plume/", "title": "Lane closures coming to I-70 in the mountains", "date_published": "2021-09-13T16:28:40+00:00", "date_modified": "2021-09-13T10:28:40+00:00"}, {"id": "https://www.denverpost.com/2021/09/13/colorado-earthquake-pritchett/", "url": "https://www.denverpost.com/2021/09/13/colorado-earthquake-pritchett/", "title": "Small early morning earthquake shakes southeast Colorado", "date_published": "2021-09-13T14:14:35+00:00", "date_modified": "2021-09-13T08:15:11+00:00"}, {"id": "https://www.denverpost.com/2021/09/13/denver-weather-monday-thunderstorms/", "url": "https://www.denverpost.com/2021/09/13/denver-weather-monday-thunderstorms/", "title": "Denver weather: Cool down, chance of thunderstorms Monday", "date_published": "2021-09-13T12:54:31+00:00", "date_modified": "2021-09-13T06:54:31+00:00"}, {"id": "https://www.denverpost.com/2021/09/13/greenwood-village-may-limit-solar-arrays/", "url": "https://www.denverpost.com/2021/09/13/greenwood-village-may-limit-solar-arrays/", "title": "Greenwood Village proposal on solar arrays prioritizes aesthetics over kilowatts", "date_published": "2021-09-13T12:00:52+00:00", "date_modified": "2021-09-12T15:15:01+00:00"}, {"id": "https://www.denverpost.com/2021/09/13/colorado-afghanistan-refugees-resettlement/", "url": "https://www.denverpost.com/2021/09/13/colorado-afghanistan-refugees-resettlement/", "title": "Colorado preparing to welcome up to 2,000 Afghans over the next six months", "date_published": "2021-09-13T12:00:51+00:00", "date_modified": "2021-09-10T16:22:37+00:00"}, {"id": "https://www.denverpost.com/2021/09/13/tri-county-douglas-county-health-department-covid/", "url": "https://www.denverpost.com/2021/09/13/tri-county-douglas-county-health-department-covid/", "title": "Tri-County Health faces uncertain future as Douglas County pulls away over COVID measures", "date_published": "2021-09-13T12:00:09+00:00", "date_modified": "2021-09-10T16:45:44+00:00"}, {"id": "https://www.denverpost.com/2021/09/12/lil-nas-x-justin-bieber-top-star-packed-mtv-vmas/", "url": "https://www.denverpost.com/2021/09/12/lil-nas-x-justin-bieber-top-star-packed-mtv-vmas/", "title": "Lil Nas X, Justin Bieber top star-packed MTV VMAs", "date_published": "2021-09-13T03:14:32+00:00", "date_modified": "2021-09-12T21:14:34+00:00"}, {"id": "https://www.denverpost.com/2021/09/12/fatal-shooting-southeast-denver/", "url": "https://www.denverpost.com/2021/09/12/fatal-shooting-southeast-denver/", "title": "Man killed after shooting in southeast Denver", "date_published": "2021-09-13T03:13:56+00:00", "date_modified": "2021-09-12T21:13:56+00:00"}]}