{"version": "https://jsonfeed.org/version/1.1", "title": "Denverite: Denver News", "home_page_url": "https://sreynen.github.io/denver-news/", "feed_url": "https://sreynen.github.io/denver-news/denverite.json", "items": [{"id": "https://www.denverpost.com/2025/08/11/jax-gratton-trans-hairstylist-death-autopsy/", "url": "https://www.denverpost.com/2025/08/11/jax-gratton-trans-hairstylist-death-autopsy/", "title": "Autopsy for Denver hairstylist Jax Gratton lists cause, manner of death as undetermined", "date_published": "2025-08-11T19:10:44+00:00", "date_modified": "2025-08-11T13:17:58+00:00"}, {"id": "https://www.denverpost.com/2025/08/11/denver-zoo-sea-lion-death/", "url": "https://www.denverpost.com/2025/08/11/denver-zoo-sea-lion-death/", "title": "Denver Zoo\u2019s huge sea lion with loud bark dies", "date_published": "2025-08-11T17:10:35+00:00", "date_modified": "2025-08-11T11:48:19+00:00"}, {"id": "https://www.denverpost.com/2025/08/11/savannah-bananas-coors-field-photos/", "url": "https://www.denverpost.com/2025/08/11/savannah-bananas-coors-field-photos/", "title": "PHOTOS: Savannah Bananas perform at Coors Field in Denver", "date_published": "2025-08-11T14:29:02+00:00", "date_modified": "2025-08-11T10:03:40+00:00"}, {"id": "https://www.denverpost.com/2025/08/11/colorado-wildfires-meeker-lee-elk/", "url": "https://www.denverpost.com/2025/08/11/colorado-wildfires-meeker-lee-elk/", "title": "Colorado wildfires: Lee fire grows to state\u2019s fifth-largest wildfire on record", "date_published": "2025-08-11T12:27:48+00:00", "date_modified": "2025-08-11T08:36:02+00:00"}, {"id": "https://www.denverpost.com/2025/08/11/jared-polis-legacy-outdoor-recreation-conservation/", "url": "https://www.denverpost.com/2025/08/11/jared-polis-legacy-outdoor-recreation-conservation/", "title": "Gov. Jared Polis wants to be remembered for making Colorado\u2019s outdoors \u2018even more amazing\u2019", "date_published": "2025-08-11T12:00:56+00:00", "date_modified": "2025-08-08T15:40:24+00:00"}, {"id": "https://www.denverpost.com/2025/08/11/aurora-crackdown-nitrous-oxide-thc-vape-shops/", "url": "https://www.denverpost.com/2025/08/11/aurora-crackdown-nitrous-oxide-thc-vape-shops/", "title": "Aurora readies crackdown on \u2018gray market\u2019 products, like nitrous oxide, at vape shops and corner stores", "date_published": "2025-08-11T12:00:43+00:00", "date_modified": "2025-08-08T16:58:33+00:00"}, {"id": "https://www.denverpost.com/2025/08/11/colorado-river-surfing-whitewater-parks/", "url": "https://www.denverpost.com/2025/08/11/colorado-river-surfing-whitewater-parks/", "title": "Where to go river surfing in landlocked Colorado", "date_published": "2025-08-11T12:00:29+00:00", "date_modified": "2025-08-08T15:13:28+00:00"}, {"id": "https://www.denverpost.com/2025/08/11/square-top-mountain-sunrise-hike/", "url": "https://www.denverpost.com/2025/08/11/square-top-mountain-sunrise-hike/", "title": "Sleep under the stars on this 13,000-foot peak for an unforgettable sunrise", "date_published": "2025-08-11T12:00:15+00:00", "date_modified": "2025-08-08T10:37:26+00:00"}, {"id": "https://www.denverpost.com/2025/08/11/cloud-nine-park-denver/", "url": "https://www.denverpost.com/2025/08/11/cloud-nine-park-denver/", "title": "Ping pong, padel and public art find a (temporary) home in private Denver park", "date_published": "2025-08-11T12:00:15+00:00", "date_modified": "2025-08-08T10:30:44+00:00"}, {"id": "https://www.denverpost.com/2025/08/11/colorado-prisons-immigration-detainers-ice-arrests/", "url": "https://www.denverpost.com/2025/08/11/colorado-prisons-immigration-detainers-ice-arrests/", "title": "Colorado prisons limit ICE cooperation more after arrests of two inmates in large immigration operation", "date_published": "2025-08-11T12:00:14+00:00", "date_modified": "2025-08-08T17:41:05+00:00"}, {"id": "https://www.denverpost.com/2025/08/10/colorado-severe-weather-front-range/", "url": "https://www.denverpost.com/2025/08/10/colorado-severe-weather-front-range/", "title": "Colorado weather: Severe thunderstorm watch active for Front Range, Eastern Plains", "date_published": "2025-08-10T18:49:39+00:00", "date_modified": "2025-08-10T13:19:37+00:00"}, {"id": "https://www.denverpost.com/2025/08/10/lee-fire-sunday-evacuations/", "url": "https://www.denverpost.com/2025/08/10/lee-fire-sunday-evacuations/", "title": "Colorado wildfires: Lee fire in Rio Blanco County expected to worsen Sunday morning", "date_published": "2025-08-10T15:39:41+00:00", "date_modified": "2025-08-10T10:34:01+00:00"}, {"id": "https://www.denverpost.com/2025/08/10/colorado-cbz-apartments-gang-takeover-claims-aurora/", "url": "https://www.denverpost.com/2025/08/10/colorado-cbz-apartments-gang-takeover-claims-aurora/", "title": "A year into Aurora\u2019s apartments saga, tenants, city officials and property owners are still dealing with the fallout", "date_published": "2025-08-10T12:00:34+00:00", "date_modified": "2025-08-08T15:20:34+00:00"}, {"id": "https://www.denverpost.com/2025/08/10/colorado-wild-horses-mustangs-darting-blm/", "url": "https://www.denverpost.com/2025/08/10/colorado-wild-horses-mustangs-darting-blm/", "title": "Colorado has a wild horse problem. Could its expanded birth control darting program be a model for the West?", "date_published": "2025-08-10T12:00:10+00:00", "date_modified": "2025-08-07T18:16:31+00:00"}, {"id": "https://www.denverpost.com/2025/08/09/colorado-weather-smoke-red-flag/", "url": "https://www.denverpost.com/2025/08/09/colorado-weather-smoke-red-flag/", "title": "Colorado weather: Critical fire conditions, heavy smoke and thunderstorms forecast", "date_published": "2025-08-09T17:46:38+00:00", "date_modified": "2025-08-09T12:03:21+00:00"}, {"id": "https://www.denverpost.com/2025/08/09/boulder-noaa-labs-cuts/", "url": "https://www.denverpost.com/2025/08/09/boulder-noaa-labs-cuts/", "title": "Uncertainty looms over Boulder\u2019s iconic NOAA labs site", "date_published": "2025-08-09T15:03:54+00:00", "date_modified": "2025-08-09T14:06:46+00:00"}, {"id": "https://www.denverpost.com/2025/08/09/colorado-lee-fire-mandatory-evacuation/", "url": "https://www.denverpost.com/2025/08/09/colorado-lee-fire-mandatory-evacuation/", "title": "Colorado wildfires: New evacuations ordered as Lee fire races south", "date_published": "2025-08-09T13:18:07+00:00", "date_modified": "2025-08-09T08:24:33+00:00"}, {"id": "https://www.denverpost.com/2025/08/08/meeker-fire-lee-elk-colorado/", "url": "https://www.denverpost.com/2025/08/08/meeker-fire-lee-elk-colorado/", "title": "When Colorado wildfires threatened this Western Slope town, neighbors showed up for each other", "date_published": "2025-08-08T22:20:45+00:00", "date_modified": "2025-08-08T18:24:16+00:00"}, {"id": "https://www.denverpost.com/2025/08/08/real-estate-investor-denver-offices/", "url": "https://www.denverpost.com/2025/08/08/real-estate-investor-denver-offices/", "title": "Real estate investor used \u2018creative\u2019 financing in purchase of Denver offices", "date_published": "2025-08-08T21:44:13+00:00", "date_modified": "2025-08-08T16:03:21+00:00"}, {"id": "https://www.denverpost.com/2025/08/08/castle-pines-mcdonalds-development-ruling/", "url": "https://www.denverpost.com/2025/08/08/castle-pines-mcdonalds-development-ruling/", "title": "Judge rules Castle Pines can block McDonald\u2019s restaurant development", "date_published": "2025-08-08T21:00:47+00:00", "date_modified": "2025-08-08T14:48:42+00:00"}, {"id": "https://www.denverpost.com/2025/08/08/colorado-mansion-sells-10m-real-estate/", "url": "https://www.denverpost.com/2025/08/08/colorado-mansion-sells-10m-real-estate/", "title": "Evergreen mansion sells for $10M, topping home sales in the Denver area for July", "date_published": "2025-08-08T21:00:00+00:00", "date_modified": "2025-08-08T13:07:46+00:00"}, {"id": "https://www.denverpost.com/2025/08/08/timothy-mcphee-guilty-plea-tax-fraud/", "url": "https://www.denverpost.com/2025/08/08/timothy-mcphee-guilty-plea-tax-fraud/", "title": "Colorado man pleads guilty in multimillion-dollar investment, tax shelter scheme", "date_published": "2025-08-08T20:01:39+00:00", "date_modified": "2025-08-08T14:31:44+00:00"}, {"id": "https://www.denverpost.com/2025/08/08/aurora-hit-run-fatal-crash/", "url": "https://www.denverpost.com/2025/08/08/aurora-hit-run-fatal-crash/", "title": "Man arrested on suspicion of Aurora hit-and-run that killed woman in wheelchair", "date_published": "2025-08-08T19:16:44+00:00", "date_modified": "2025-08-08T13:44:23+00:00"}, {"id": "https://www.denverpost.com/2025/08/08/tetra-cannabis-lounge-denver-employee/", "url": "https://www.denverpost.com/2025/08/08/tetra-cannabis-lounge-denver-employee/", "title": "Denver employee \u2018no longer with the city\u2019 after incident at cannabis club", "date_published": "2025-08-08T18:06:13+00:00", "date_modified": "2025-08-08T12:05:39+00:00"}, {"id": "https://www.denverpost.com/2025/08/08/denver-public-schools-contract-negotiations-union/", "url": "https://www.denverpost.com/2025/08/08/denver-public-schools-contract-negotiations-union/", "title": "DPS to restart negotiations with office staff \u2014 now with a mediator \u2014 after reaching impasse", "date_published": "2025-08-08T16:16:44+00:00", "date_modified": "2025-08-08T12:23:01+00:00"}, {"id": "https://www.denverpost.com/2025/08/08/colorado-denver-sanctuary-jurisdictions-list-immigration/", "url": "https://www.denverpost.com/2025/08/08/colorado-denver-sanctuary-jurisdictions-list-immigration/", "title": "Colorado, Denver are on new federal \u2018sanctuary jurisdictions\u2019 list \u2014 but this time, there are fewer targets", "date_published": "2025-08-08T16:05:47+00:00", "date_modified": "2025-08-08T12:06:48+00:00"}, {"id": "https://www.denverpost.com/2025/08/08/i70-denver-crash-pedestrian-killed/", "url": "https://www.denverpost.com/2025/08/08/i70-denver-crash-pedestrian-killed/", "title": "Pedestrian killed on I-70 in Denver", "date_published": "2025-08-08T12:58:38+00:00", "date_modified": "2025-08-08T07:15:53+00:00"}, {"id": "https://www.denverpost.com/2025/08/08/park-hill-vibrant-denver-bond-ballot/", "url": "https://www.denverpost.com/2025/08/08/park-hill-vibrant-denver-bond-ballot/", "title": "Former Park Hill Golf Course is tabbed for $70 million full-park buildout in bond package", "date_published": "2025-08-08T12:00:42+00:00", "date_modified": "2025-08-07T18:53:36+00:00"}, {"id": "https://www.denverpost.com/2025/08/08/palisade-peaches-recipes/", "url": "https://www.denverpost.com/2025/08/08/palisade-peaches-recipes/", "title": "Here\u2019s why Palisade peaches are so delicious. (Plus: a couple of recipes)", "date_published": "2025-08-08T12:00:26+00:00", "date_modified": "2025-08-07T12:00:13+00:00"}, {"id": "https://www.denverpost.com/2025/08/08/tetra-cannabis-lounge-license-denver/", "url": "https://www.denverpost.com/2025/08/08/tetra-cannabis-lounge-license-denver/", "title": "Denver cannabis lounge accused of violating law, could lose its license", "date_published": "2025-08-08T12:00:16+00:00", "date_modified": "2025-08-07T17:06:50+00:00"}]}