{"version": "https://jsonfeed.org/version/1.1", "title": "Denverite: Denver News", "home_page_url": "https://sreynen.github.io/denver-news/", "feed_url": "https://sreynen.github.io/denver-news/denverite.json", "items": [{"id": "https://www.denverpost.com/2025/09/13/thunderstorms-severe-weather-colorado/", "url": "https://www.denverpost.com/2025/09/13/thunderstorms-severe-weather-colorado/", "title": "Colorado weather: Thunderstorms, hail and strong winds expected this afternoon", "date_published": "2025-09-13T16:54:31+00:00", "date_modified": "2025-09-13T10:54:31+00:00"}, {"id": "https://www.denverpost.com/2025/09/13/colorado-school-shooting-evergreen-resource-officers/", "url": "https://www.denverpost.com/2025/09/13/colorado-school-shooting-evergreen-resource-officers/", "title": "Parent groups raised concerns about resource officers before Evergreen High School shooting", "date_published": "2025-09-13T12:00:58+00:00", "date_modified": "2025-09-12T18:00:57+00:00"}, {"id": "https://www.denverpost.com/2025/09/13/colorado-lone-tree-arrest-homicide/", "url": "https://www.denverpost.com/2025/09/13/colorado-lone-tree-arrest-homicide/", "title": "Lone Tree police arrest man in connection with woman\u2019s death", "date_published": "2025-09-13T12:00:25+00:00", "date_modified": "2025-09-12T17:56:29+00:00"}, {"id": "https://www.denverpost.com/2025/09/12/body-recovered-from-carter-lake-where-kayaker-reported-missing/", "url": "https://www.denverpost.com/2025/09/12/body-recovered-from-carter-lake-where-kayaker-reported-missing/", "title": "Body recovered from Carter Lake, where kayaker reported missing", "date_published": "2025-09-13T00:06:30+00:00", "date_modified": "2025-09-13T09:19:30+00:00"}, {"id": "https://www.denverpost.com/2025/09/12/evergreen-high-school-shooter-extremism/", "url": "https://www.denverpost.com/2025/09/12/evergreen-high-school-shooter-extremism/", "title": "Evergreen High School shooter\u2019s online footprint reflects new wave of extremism, experts say", "date_published": "2025-09-12T20:54:59+00:00", "date_modified": "2025-09-12T15:07:11+00:00"}, {"id": "https://www.denverpost.com/2025/09/12/colorado-funeral-director-return-to-nature-withdraw-guilty-plea/", "url": "https://www.denverpost.com/2025/09/12/colorado-funeral-director-return-to-nature-withdraw-guilty-plea/", "title": "Colorado funeral director who acknowledged abusing 191 corpses withdraws guilty plea", "date_published": "2025-09-12T18:52:02+00:00", "date_modified": "2025-09-12T12:56:10+00:00"}, {"id": "https://www.denverpost.com/2025/09/12/yadira-caraveo-drops-out-congress/", "url": "https://www.denverpost.com/2025/09/12/yadira-caraveo-drops-out-congress/", "title": "Democrat Yadira Caraveo drops bid to retake 8th Congressional District seat", "date_published": "2025-09-12T18:50:59+00:00", "date_modified": "2025-09-12T13:09:02+00:00"}, {"id": "https://www.denverpost.com/2025/09/12/colorado-denver-police-homicide/", "url": "https://www.denverpost.com/2025/09/12/colorado-denver-police-homicide/", "title": "Denver police arrest juvenile in connection with weekend shooting death", "date_published": "2025-09-12T18:34:26+00:00", "date_modified": "2025-09-12T12:34:26+00:00"}, {"id": "https://www.denverpost.com/2025/09/12/ben-crump-aurora-police-shooting/", "url": "https://www.denverpost.com/2025/09/12/ben-crump-aurora-police-shooting/", "title": "Civil rights attorney Ben Crump pledges justice for Black man shot by Aurora police", "date_published": "2025-09-12T18:25:44+00:00", "date_modified": "2025-09-12T12:32:24+00:00"}, {"id": "https://www.denverpost.com/2025/09/12/colorado-springs-high-school-gun/", "url": "https://www.denverpost.com/2025/09/12/colorado-springs-high-school-gun/", "title": "Handgun, airsoft gun confiscated at Colorado Springs high school", "date_published": "2025-09-12T18:12:52+00:00", "date_modified": "2025-09-12T12:12:52+00:00"}, {"id": "https://www.denverpost.com/2025/09/12/safeway-grocer-closures-jobs/", "url": "https://www.denverpost.com/2025/09/12/safeway-grocer-closures-jobs/", "title": "Safeway\u2019s plan to close 10 Colorado stores sparks concern over access to groceries, job losses", "date_published": "2025-09-12T16:56:44+00:00", "date_modified": "2025-09-12T10:56:44+00:00"}, {"id": "https://www.denverpost.com/2025/09/12/foraged-restaurant-dairy-block-denver-closed/", "url": "https://www.denverpost.com/2025/09/12/foraged-restaurant-dairy-block-denver-closed/", "title": "Sushi restaurant at Denver\u2019s Dairy Block announces closure", "date_published": "2025-09-12T16:52:30+00:00", "date_modified": "2025-09-12T10:56:46+00:00"}, {"id": "https://www.denverpost.com/2025/09/12/rtd-a-line-shutdown/", "url": "https://www.denverpost.com/2025/09/12/rtd-a-line-shutdown/", "title": "Early morning copper wire theft forces RTD to shut down segment of A Line", "date_published": "2025-09-12T16:46:18+00:00", "date_modified": "2025-09-12T11:13:28+00:00"}, {"id": "https://www.denverpost.com/2025/09/12/q-house-colfax-closes-chinese/", "url": "https://www.denverpost.com/2025/09/12/q-house-colfax-closes-chinese/", "title": "Michelin-recommended modern Chinese restaurant closes on Colfax", "date_published": "2025-09-12T16:33:13+00:00", "date_modified": "2025-09-12T11:11:47+00:00"}, {"id": "https://www.denverpost.com/2025/09/12/colorado-school-shooting-evergreen/", "url": "https://www.denverpost.com/2025/09/12/colorado-school-shooting-evergreen/", "title": "2 students injured in Evergreen High School shooting remain in critical condition", "date_published": "2025-09-12T16:00:38+00:00", "date_modified": "2025-09-12T10:09:05+00:00"}, {"id": "https://www.denverpost.com/2025/09/12/16th-street-rtd-shuttle/", "url": "https://www.denverpost.com/2025/09/12/16th-street-rtd-shuttle/", "title": "RTD\u2019s 16th Street shuttles to fully resume service Oct. 5", "date_published": "2025-09-12T14:33:19+00:00", "date_modified": "2025-09-12T08:33:19+00:00"}, {"id": "https://www.denverpost.com/2025/09/12/aurora-rtd-bus-crash-fatal/", "url": "https://www.denverpost.com/2025/09/12/aurora-rtd-bus-crash-fatal/", "title": "Woman dies, infant injured after SUV crashes head-on into RTD bus in Aurora", "date_published": "2025-09-12T13:05:51+00:00", "date_modified": "2025-09-12T07:05:51+00:00"}, {"id": "https://www.denverpost.com/2025/09/12/colorado-congress-health-insurance/", "url": "https://www.denverpost.com/2025/09/12/colorado-congress-health-insurance/", "title": "In Congress, Colorado representatives push to limit health care losses", "date_published": "2025-09-12T12:00:25+00:00", "date_modified": "2025-09-11T17:04:44+00:00"}, {"id": "https://www.denverpost.com/2025/09/12/rougarou-restaurant-opens-denver/", "url": "https://www.denverpost.com/2025/09/12/rougarou-restaurant-opens-denver/", "title": "James Beard nominees serving Southern food with style and spunk", "date_published": "2025-09-12T12:00:24+00:00", "date_modified": "2025-09-11T15:13:12+00:00"}, {"id": "https://www.denverpost.com/2025/09/12/federal-theatre-reopening-concerts-denver/", "url": "https://www.denverpost.com/2025/09/12/federal-theatre-reopening-concerts-denver/", "title": "Haunted or not, renovated Federal Theatre opens next week with free concert", "date_published": "2025-09-12T11:00:23+00:00", "date_modified": "2025-09-11T13:16:28+00:00"}, {"id": "https://www.denverpost.com/2025/09/11/law-enforcement-shooting-at-evergreen-walmart-tied-to-i-70-crash-closure-near-lookout-mountain/", "url": "https://www.denverpost.com/2025/09/11/law-enforcement-shooting-at-evergreen-walmart-tied-to-i-70-crash-closure-near-lookout-mountain/", "title": "Law enforcement shooting at Evergreen Walmart tied to I-70 crash, closure near Lookout Mountain", "date_published": "2025-09-12T02:16:41+00:00", "date_modified": "2025-09-11T20:16:41+00:00"}, {"id": "https://www.denverpost.com/2025/09/11/crews-responding-to-reported-drowning-at-carter-lake/", "url": "https://www.denverpost.com/2025/09/11/crews-responding-to-reported-drowning-at-carter-lake/", "title": "Crews searching for kayaker reported missing in Carter Lake", "date_published": "2025-09-12T00:29:43+00:00", "date_modified": "2025-09-12T07:37:00+00:00"}, {"id": "https://www.denverpost.com/2025/09/11/murder-suicide-pinewood-springs-larimer-county/", "url": "https://www.denverpost.com/2025/09/11/murder-suicide-pinewood-springs-larimer-county/", "title": "Two adults dead in apparent murder-suicide in Larimer County\u2019s Pinewood Springs", "date_published": "2025-09-11T21:33:34+00:00", "date_modified": "2025-09-11T16:49:34+00:00"}, {"id": "https://www.denverpost.com/2025/09/11/newborn-cold-case-brighton-unsolved/", "url": "https://www.denverpost.com/2025/09/11/newborn-cold-case-brighton-unsolved/", "title": "Family of newborn found dead outside Brighton repair shop in 2002 still sought", "date_published": "2025-09-11T20:04:09+00:00", "date_modified": "2025-09-11T16:54:16+00:00"}, {"id": "https://www.denverpost.com/2025/09/11/colorado-school-shooting-suspect-desmond-holly/", "url": "https://www.denverpost.com/2025/09/11/colorado-school-shooting-suspect-desmond-holly/", "title": "Who is Evergreen High School shooting suspect Desmond Holly?", "date_published": "2025-09-11T17:56:45+00:00", "date_modified": "2025-09-11T12:32:39+00:00"}, {"id": "https://www.denverpost.com/2025/09/11/lockdown-fairview-high-southern-hills-boulder/", "url": "https://www.denverpost.com/2025/09/11/lockdown-fairview-high-southern-hills-boulder/", "title": "Reported man with gun near Boulder\u2019s Fairview High School was runner holding phone, police say", "date_published": "2025-09-11T17:08:56+00:00", "date_modified": "2025-09-11T15:13:59+00:00"}, {"id": "https://www.denverpost.com/2025/09/11/evergreen-high-school-shooting-colorado-updates/", "url": "https://www.denverpost.com/2025/09/11/evergreen-high-school-shooting-colorado-updates/", "title": "In wake of Evergreen High School shooting, 1 teen remains in critical condition", "date_published": "2025-09-11T13:49:38+00:00", "date_modified": "2025-09-11T08:30:41+00:00"}, {"id": "https://www.denverpost.com/2025/09/11/evergreen-colorado-school-shooting-closures/", "url": "https://www.denverpost.com/2025/09/11/evergreen-colorado-school-shooting-closures/", "title": "Classes canceled at Evergreen High School after fatal shooting", "date_published": "2025-09-11T12:44:35+00:00", "date_modified": "2025-09-11T06:44:35+00:00"}, {"id": "https://www.denverpost.com/2025/09/11/guanella-pass-parking-fall-colors/", "url": "https://www.denverpost.com/2025/09/11/guanella-pass-parking-fall-colors/", "title": "Leaf-peepers beware: Heightened parking enforcement planned for Guanella Pass this month", "date_published": "2025-09-11T12:00:54+00:00", "date_modified": "2025-09-10T16:01:40+00:00"}, {"id": "https://www.denverpost.com/2025/09/11/dachshund-wiener-dog-races-oktoberfest-colorado/", "url": "https://www.denverpost.com/2025/09/11/dachshund-wiener-dog-races-oktoberfest-colorado/", "title": "\u2018Go, wiener, go!\u2019 5 places to see dachshund races in Colorado this fall", "date_published": "2025-09-11T12:00:45+00:00", "date_modified": "2025-09-10T11:57:32+00:00"}]}