{"version": "https://jsonfeed.org/version/1.1", "title": "Denverite: Denver News", "home_page_url": "https://sreynen.github.io/denver-news/", "feed_url": "https://sreynen.github.io/denver-news/denverite.json", "items": [{"id": "https://www.denverpost.com/2022/06/27/lauren-boebert-colorado-shooters-restaurant/", "url": "https://www.denverpost.com/2022/06/27/lauren-boebert-colorado-shooters-restaurant/", "title": "Lauren Boebert\u2019s gun-themed restaurant, Shooters, might have to move or close", "date_published": "2022-06-27T16:46:45+00:00", "date_modified": "2022-06-27T10:48:20+00:00"}, {"id": "https://www.denverpost.com/2022/06/27/avalanche-stanley-cup-celebration-arrests/", "url": "https://www.denverpost.com/2022/06/27/avalanche-stanley-cup-celebration-arrests/", "title": "One arrest made in relation to Avalanche Stanley Cup celebration", "date_published": "2022-06-27T15:08:58+00:00", "date_modified": "2022-06-27T09:08:58+00:00"}, {"id": "https://www.denverpost.com/2022/06/27/colorado-wic-food-assistance/", "url": "https://www.denverpost.com/2022/06/27/colorado-wic-food-assistance/", "title": "Colorado struggles to enroll families in WIC food-assistance program, new report finds", "date_published": "2022-06-27T15:00:07+00:00", "date_modified": "2022-06-27T09:00:07+00:00"}, {"id": "https://www.denverpost.com/2022/06/27/pueblo-police-fatal-shooting/", "url": "https://www.denverpost.com/2022/06/27/pueblo-police-fatal-shooting/", "title": "Pueblo police shoot and kill armed man on Sunday", "date_published": "2022-06-27T13:03:10+00:00", "date_modified": "2022-06-27T07:03:10+00:00"}, {"id": "https://www.denverpost.com/2022/06/27/denver-weather-sunny-thunderstorms-monday/", "url": "https://www.denverpost.com/2022/06/27/denver-weather-sunny-thunderstorms-monday/", "title": "Denver weather: High of 85 expected Monday, slight chance for thunderstorms", "date_published": "2022-06-27T12:47:43+00:00", "date_modified": "2022-06-27T06:49:07+00:00"}, {"id": "https://www.denverpost.com/2022/06/27/colorado-transportation-fees-delivery-uber-lyft/", "url": "https://www.denverpost.com/2022/06/27/colorado-transportation-fees-delivery-uber-lyft/", "title": "Ordering from Amazon or taking a Lyft ride? You\u2019re about to kick in money for roads, transit and electric vehicles.", "date_published": "2022-06-27T12:00:33+00:00", "date_modified": "2022-06-27T06:03:26+00:00"}, {"id": "https://www.denverpost.com/2022/06/27/colorado-opioid-settlement-money/", "url": "https://www.denverpost.com/2022/06/27/colorado-opioid-settlement-money/", "title": "$400 million in long-awaited opioid settlement money will begin to go out to Colorado communities by late summer", "date_published": "2022-06-27T12:00:25+00:00", "date_modified": "2022-06-27T06:03:29+00:00"}, {"id": "https://www.denverpost.com/2022/06/27/cherry-creek-arts-festival-returns-2022/", "url": "https://www.denverpost.com/2022/06/27/cherry-creek-arts-festival-returns-2022/", "title": "The Cherry Creek Arts Festival returns to the business of art \u2014 and music, food and crowds", "date_published": "2022-06-27T12:00:07+00:00", "date_modified": "2022-06-24T10:50:32+00:00"}, {"id": "https://www.denverpost.com/2022/06/27/torchys-tacos-smashburger-bonchon-new-location-denver/", "url": "https://www.denverpost.com/2022/06/27/torchys-tacos-smashburger-bonchon-new-location-denver/", "title": "Torchy\u2019s Tacos, Smashburger and Bonchon open new Denver-area locations", "date_published": "2022-06-27T12:00:05+00:00", "date_modified": "2022-06-24T16:05:31+00:00"}, {"id": "https://www.denverpost.com/2022/06/26/photos-2022-denver-pride-parade-returns/", "url": "https://www.denverpost.com/2022/06/26/photos-2022-denver-pride-parade-returns/", "title": "PHOTOS: 2022 Denver Pride Parade returns", "date_published": "2022-06-27T00:51:51+00:00", "date_modified": "2022-06-26T18:51:51+00:00"}, {"id": "https://www.denverpost.com/2022/06/26/post-premium-top-stories-for-the-week-of-june-20-26/", "url": "https://www.denverpost.com/2022/06/26/post-premium-top-stories-for-the-week-of-june-20-26/", "title": "Post Premium: Top stories for the week of June 20-26", "date_published": "2022-06-26T12:00:11+00:00", "date_modified": "2022-06-26T06:03:21+00:00"}, {"id": "https://www.denverpost.com/2022/06/26/democrats-meddle-colorado-republicans-election-2022/", "url": "https://www.denverpost.com/2022/06/26/democrats-meddle-colorado-republicans-election-2022/", "title": "Democrats appear to be helping Colorado election deniers win primaries. Here\u2019s why", "date_published": "2022-06-26T12:00:09+00:00", "date_modified": "2022-06-26T06:03:24+00:00"}, {"id": "https://www.denverpost.com/2022/06/25/tivoli-quad-stanley-cup-watch-party-canceled/", "url": "https://www.denverpost.com/2022/06/25/tivoli-quad-stanley-cup-watch-party-canceled/", "title": "Tivoli Quad will not host watch party for Game 6 of Stanley Cup Final between Avalanche and Lightning", "date_published": "2022-06-26T00:42:53+00:00", "date_modified": "2022-06-25T18:44:06+00:00"}, {"id": "https://www.denverpost.com/2022/06/25/power-outage-commerce-city/", "url": "https://www.denverpost.com/2022/06/25/power-outage-commerce-city/", "title": "Power outage hits metro area including southern portion of Commerce City", "date_published": "2022-06-25T22:29:13+00:00", "date_modified": "2022-06-25T16:29:13+00:00"}, {"id": "https://www.denverpost.com/2022/06/25/denver-pridefest-returns-photos-2022/", "url": "https://www.denverpost.com/2022/06/25/denver-pridefest-returns-photos-2022/", "title": "PHOTOS: Denver PrideFest returns to Civic Center for 2022", "date_published": "2022-06-25T22:25:54+00:00", "date_modified": "2022-06-25T16:25:54+00:00"}, {"id": "https://www.denverpost.com/2022/06/25/hanging-lake-trail-reopens-mudslide-damage/", "url": "https://www.denverpost.com/2022/06/25/hanging-lake-trail-reopens-mudslide-damage/", "title": "Hanging Lake trail reopens after extensive mudslide damage", "date_published": "2022-06-25T20:43:16+00:00", "date_modified": "2022-06-25T15:25:08+00:00"}, {"id": "https://www.denverpost.com/2022/06/25/bear-hunt-colorado-attack/", "url": "https://www.denverpost.com/2022/06/25/bear-hunt-colorado-attack/", "title": "Bear hunt underway after attack in southern Colorado", "date_published": "2022-06-25T20:19:27+00:00", "date_modified": "2022-06-25T14:19:27+00:00"}, {"id": "https://www.denverpost.com/2022/06/25/life-choices-longmont-vandalized/", "url": "https://www.denverpost.com/2022/06/25/life-choices-longmont-vandalized/", "title": "Life Choices, which helps pregnant women, in Longmont is set on fire and vandalized", "date_published": "2022-06-25T19:41:52+00:00", "date_modified": "2022-06-25T13:42:20+00:00"}, {"id": "https://www.denverpost.com/2022/06/25/denver-weather-cloudy-cooler-weekend/", "url": "https://www.denverpost.com/2022/06/25/denver-weather-cloudy-cooler-weekend/", "title": "Denver weather: Cloudy and cooler temperatures expected through the weekend", "date_published": "2022-06-25T16:29:04+00:00", "date_modified": "2022-06-25T10:31:37+00:00"}, {"id": "https://www.denverpost.com/2022/06/24/jeremiah-cannady-homicide-shooting-aurora/", "url": "https://www.denverpost.com/2022/06/24/jeremiah-cannady-homicide-shooting-aurora/", "title": "Man shot in Aurora dies at a local hospital three days later", "date_published": "2022-06-25T01:47:51+00:00", "date_modified": "2022-06-24T19:47:51+00:00"}, {"id": "https://www.denverpost.com/2022/06/24/denver-protests-roe-v-wade-abortion/", "url": "https://www.denverpost.com/2022/06/24/denver-protests-roe-v-wade-abortion/", "title": "Protests underway at the state Capitol following Supreme Court ruling on Roe v. Wade", "date_published": "2022-06-25T00:44:00+00:00", "date_modified": "2022-06-24T20:17:57+00:00"}, {"id": "https://www.denverpost.com/2022/06/24/jeffco-cyclists-crash-hit-run-arrest/", "url": "https://www.denverpost.com/2022/06/24/jeffco-cyclists-crash-hit-run-arrest/", "title": "Suspect arrested in connection to \u201cdeliberate\u201d hit-and-run of 2 cyclists in Jefferson County", "date_published": "2022-06-24T23:56:52+00:00", "date_modified": "2022-06-24T18:11:59+00:00"}, {"id": "https://www.denverpost.com/2022/06/24/colorado-abortion-safe-haven/", "url": "https://www.denverpost.com/2022/06/24/colorado-abortion-safe-haven/", "title": "Colorado, now an abortion \u201csafe haven,\u201d prepares for new challenges", "date_published": "2022-06-24T22:49:41+00:00", "date_modified": "2022-06-24T17:11:56+00:00"}, {"id": "https://www.denverpost.com/2022/06/24/federal-court-blocks-fda-ban-on-juul-e-cigarette-sales-in-us/", "url": "https://www.denverpost.com/2022/06/24/federal-court-blocks-fda-ban-on-juul-e-cigarette-sales-in-us/", "title": "Federal court blocks FDA ban on Juul e-cigarette sales in U.S.", "date_published": "2022-06-24T22:13:24+00:00", "date_modified": "2022-06-24T16:58:07+00:00"}, {"id": "https://www.denverpost.com/2022/06/24/roe-v-wade-overturned-colorado-abortion-law-politics-reaction/", "url": "https://www.denverpost.com/2022/06/24/roe-v-wade-overturned-colorado-abortion-law-politics-reaction/", "title": "What Colorado\u2019s leaders are saying about Roe v. Wade being overturned", "date_published": "2022-06-24T16:43:48+00:00", "date_modified": "2022-06-24T10:48:37+00:00"}, {"id": "https://www.denverpost.com/2022/06/24/denver-weather-weekend-rain/", "url": "https://www.denverpost.com/2022/06/24/denver-weather-weekend-rain/", "title": "Denver weather: Cooler temperatures, rain in store this weekend", "date_published": "2022-06-24T13:51:11+00:00", "date_modified": "2022-06-24T07:51:11+00:00"}, {"id": "https://www.denverpost.com/2022/06/24/denver-black-queer-collective/", "url": "https://www.denverpost.com/2022/06/24/denver-black-queer-collective/", "title": "Denver Black Queer Collective makes space for joy, friendship, healing", "date_published": "2022-06-24T12:09:17+00:00", "date_modified": "2022-06-24T06:12:22+00:00"}, {"id": "https://www.denverpost.com/2022/06/23/alan-haley-mill-cyclists-jefferson-county/", "url": "https://www.denverpost.com/2022/06/23/alan-haley-mill-cyclists-jefferson-county/", "title": "Driver suspected of intentionally striking two bicyclists in Jefferson County is in custody", "date_published": "2022-06-24T02:50:02+00:00", "date_modified": "2022-06-23T21:03:56+00:00"}, {"id": "https://www.denverpost.com/2022/06/23/denver-mayor-hancock-douglas-county-mountain-park/", "url": "https://www.denverpost.com/2022/06/23/denver-mayor-hancock-douglas-county-mountain-park/", "title": "Denver Mayor Hancock\u2019s slams door on idea that Douglas County could take over mountain park", "date_published": "2022-06-24T01:30:32+00:00", "date_modified": "2022-06-23T19:33:20+00:00"}, {"id": "https://www.denverpost.com/2022/06/23/douglas-county-school-board-audio-superintendent-fired/", "url": "https://www.denverpost.com/2022/06/23/douglas-county-school-board-audio-superintendent-fired/", "title": "Audio captured Douglas County school board members give ultimatum to former superintendent: \u201cWe don\u2019t want to make this super public\u201d", "date_published": "2022-06-23T22:32:27+00:00", "date_modified": "2022-06-23T17:03:16+00:00"}]}