{"version": "https://jsonfeed.org/version/1.1", "title": "Denverite: Denver News", "home_page_url": "https://sreynen.github.io/denver-news/", "feed_url": "https://sreynen.github.io/denver-news/denverite.json", "items": [{"id": "https://www.denverpost.com/2025/08/08/i70-denver-crash-pedestrian-killed/", "url": "https://www.denverpost.com/2025/08/08/i70-denver-crash-pedestrian-killed/", "title": "Pedestrian killed on I-70 in Denver", "date_published": "2025-08-08T12:58:38+00:00", "date_modified": "2025-08-08T07:15:53+00:00"}, {"id": "https://www.denverpost.com/2025/08/08/park-hill-vibrant-denver-bond-ballot/", "url": "https://www.denverpost.com/2025/08/08/park-hill-vibrant-denver-bond-ballot/", "title": "Former Park Hill Golf Course is tabbed for $70 million full-park buildout in bond package", "date_published": "2025-08-08T12:00:42+00:00", "date_modified": "2025-08-07T18:53:36+00:00"}, {"id": "https://www.denverpost.com/2025/08/08/palisade-peaches-recipes/", "url": "https://www.denverpost.com/2025/08/08/palisade-peaches-recipes/", "title": "Here\u2019s why Palisade peaches are so delicious. (Plus: a couple of recipes)", "date_published": "2025-08-08T12:00:26+00:00", "date_modified": "2025-08-07T12:00:13+00:00"}, {"id": "https://www.denverpost.com/2025/08/08/tetra-cannabis-lounge-license-denver/", "url": "https://www.denverpost.com/2025/08/08/tetra-cannabis-lounge-license-denver/", "title": "Denver cannabis lounge accused of violating law, could lose its license", "date_published": "2025-08-08T12:00:16+00:00", "date_modified": "2025-08-07T17:06:50+00:00"}, {"id": "https://www.denverpost.com/2025/08/08/restaurant-loans-16th-street-denver/", "url": "https://www.denverpost.com/2025/08/08/restaurant-loans-16th-street-denver/", "title": "$1.4 million in loans for ice cream, tea shops hint at a future for 16th Street", "date_published": "2025-08-08T12:00:07+00:00", "date_modified": "2025-08-07T16:34:54+00:00"}, {"id": "https://www.denverpost.com/2025/08/07/meeker-elk-lee-fires-under-threat/", "url": "https://www.denverpost.com/2025/08/07/meeker-elk-lee-fires-under-threat/", "title": "Western Slope town under threat as two wildfires close in", "date_published": "2025-08-08T02:29:17+00:00", "date_modified": "2025-08-07T20:33:14+00:00"}, {"id": "https://www.denverpost.com/2025/08/07/colorado-wildfires-lee-elk-stoner-mesa-twelve-windy-gap/", "url": "https://www.denverpost.com/2025/08/07/colorado-wildfires-lee-elk-stoner-mesa-twelve-windy-gap/", "title": "Colorado wildfires: Lee fire continues to grow, now charring more than 60,000 acres", "date_published": "2025-08-08T01:56:57+00:00", "date_modified": "2025-08-08T09:19:28+00:00"}, {"id": "https://www.denverpost.com/2025/08/07/aurora-detective-hoarded-case-files/", "url": "https://www.denverpost.com/2025/08/07/aurora-detective-hoarded-case-files/", "title": "Retired Aurora police detective kept investigative material under floorboards, chief says", "date_published": "2025-08-07T21:13:04+00:00", "date_modified": "2025-08-07T18:32:15+00:00"}, {"id": "https://www.denverpost.com/2025/08/07/pub-on-pearl-closing/", "url": "https://www.denverpost.com/2025/08/07/pub-on-pearl-closing/", "title": "Pub on Pearl, a longtime Wash Park dive bar, will close permanently Sunday", "date_published": "2025-08-07T21:00:06+00:00", "date_modified": "2025-08-07T10:35:47+00:00"}, {"id": "https://www.denverpost.com/2025/08/07/denver-entrepreneur-16th-street/", "url": "https://www.denverpost.com/2025/08/07/denver-entrepreneur-16th-street/", "title": "Denver entrepreneur looks to transform 16th Street downtown with $3M in DDA funds", "date_published": "2025-08-07T21:00:05+00:00", "date_modified": "2025-08-07T10:13:45+00:00"}, {"id": "https://www.denverpost.com/2025/08/07/great-american-beer-festival-liquor-tickets/", "url": "https://www.denverpost.com/2025/08/07/great-american-beer-festival-liquor-tickets/", "title": "Great American Beer Festival is now serving \u2026 liquor?", "date_published": "2025-08-07T18:53:10+00:00", "date_modified": "2025-08-07T13:29:34+00:00"}, {"id": "https://www.denverpost.com/2025/08/07/south-park-episode-ice-ball-arena-denver/", "url": "https://www.denverpost.com/2025/08/07/south-park-episode-ice-ball-arena-denver/", "title": "\u2018South Park\u2019: ICE raids Denver\u2019s Ball Arena in new episode", "date_published": "2025-08-07T17:10:49+00:00", "date_modified": "2025-08-07T11:17:47+00:00"}, {"id": "https://www.denverpost.com/2025/08/07/jefferson-county-colorado-cat-plague/", "url": "https://www.denverpost.com/2025/08/07/jefferson-county-colorado-cat-plague/", "title": "Jefferson County cat dies of plague", "date_published": "2025-08-07T15:49:16+00:00", "date_modified": "2025-08-07T11:30:38+00:00"}, {"id": "https://www.denverpost.com/2025/08/07/meeker-fire-update-colorado-wildfires/", "url": "https://www.denverpost.com/2025/08/07/meeker-fire-update-colorado-wildfires/", "title": "Colorado wildfires: Meeker fires scorch more than 59,000 acres", "date_published": "2025-08-07T13:13:48+00:00", "date_modified": "2025-08-07T08:10:02+00:00"}, {"id": "https://www.denverpost.com/2025/08/07/denver-crash-pedestrian-parker-road/", "url": "https://www.denverpost.com/2025/08/07/denver-crash-pedestrian-parker-road/", "title": "1 dead in crash involving pedestrian in Denver\u2019s Hampden neighborhood", "date_published": "2025-08-07T12:31:44+00:00", "date_modified": "2025-08-07T06:49:25+00:00"}, {"id": "https://www.denverpost.com/2025/08/07/denver-cooling-center-weather-heat/", "url": "https://www.denverpost.com/2025/08/07/denver-cooling-center-weather-heat/", "title": "Denver opens cooling centers for 100-degree forecast", "date_published": "2025-08-07T12:00:29+00:00", "date_modified": "2025-08-06T19:46:34+00:00"}, {"id": "https://www.denverpost.com/2025/08/07/colorado-outdoor-brand-ambassadors/", "url": "https://www.denverpost.com/2025/08/07/colorado-outdoor-brand-ambassadors/", "title": "Colorado-based Osprey among several outdoor gear companies relying on brand ambassadors", "date_published": "2025-08-07T12:00:28+00:00", "date_modified": "2025-08-06T10:02:24+00:00"}, {"id": "https://www.denverpost.com/2025/08/07/vaccines-covid-pregnant-kids-rfk/", "url": "https://www.denverpost.com/2025/08/07/vaccines-covid-pregnant-kids-rfk/", "title": "No changes to routine vaccines, but pregnant women might have to pay for COVID shots", "date_published": "2025-08-07T12:00:17+00:00", "date_modified": "2025-08-06T12:49:31+00:00"}, {"id": "https://www.denverpost.com/2025/08/07/where-to-eat-bison-in-colorado/", "url": "https://www.denverpost.com/2025/08/07/where-to-eat-bison-in-colorado/", "title": "From fast casual to Michelin fine dining, bison is a Colorado menu staple", "date_published": "2025-08-07T12:00:03+00:00", "date_modified": "2025-08-06T11:38:27+00:00"}, {"id": "https://www.denverpost.com/2025/08/06/denver-airport-ground-stop-united/", "url": "https://www.denverpost.com/2025/08/06/denver-airport-ground-stop-united/", "title": "United flights in Denver, nationwide grounded for \u2018technology issue\u2019", "date_published": "2025-08-07T00:39:35+00:00", "date_modified": "2025-08-06T20:17:24+00:00"}, {"id": "https://www.denverpost.com/2025/08/06/cole-church-cafe/", "url": "https://www.denverpost.com/2025/08/06/cole-church-cafe/", "title": "This 140-year-old church in Denver\u2019s Cole neighborhood is about to become a cafe", "date_published": "2025-08-06T21:00:59+00:00", "date_modified": "2025-08-06T12:35:04+00:00"}, {"id": "https://www.denverpost.com/2025/08/06/walgreens-stores-closing-denver-quebec-colfax/", "url": "https://www.denverpost.com/2025/08/06/walgreens-stores-closing-denver-quebec-colfax/", "title": "Two more Denver Walgreens locations will close in September", "date_published": "2025-08-06T21:00:56+00:00", "date_modified": "2025-08-06T11:44:50+00:00"}, {"id": "https://www.denverpost.com/2025/08/06/residents-interns-union-cu-labor-complaint/", "url": "https://www.denverpost.com/2025/08/06/residents-interns-union-cu-labor-complaint/", "title": "Union for medical residents, fellows files labor complaint against CU School of Medicine", "date_published": "2025-08-06T20:51:30+00:00", "date_modified": "2025-08-06T16:41:32+00:00"}, {"id": "https://www.denverpost.com/2025/08/06/denver-weather-temperature-thursday/", "url": "https://www.denverpost.com/2025/08/06/denver-weather-temperature-thursday/", "title": "Denver weather: Record heat expected across metro, Front Range", "date_published": "2025-08-06T20:27:36+00:00", "date_modified": "2025-08-06T15:04:58+00:00"}, {"id": "https://www.denverpost.com/2025/08/06/dia-airport-nuclear-power/", "url": "https://www.denverpost.com/2025/08/06/dia-airport-nuclear-power/", "title": "Denver airport to explore nuclear energy as option to power growth", "date_published": "2025-08-06T18:45:21+00:00", "date_modified": "2025-08-06T11:57:35+00:00"}, {"id": "https://www.denverpost.com/2025/08/06/colorado-red-flag-severe-weather/", "url": "https://www.denverpost.com/2025/08/06/colorado-red-flag-severe-weather/", "title": "Colorado weather: Red flag, heat and smoke advisories active statewide", "date_published": "2025-08-06T18:40:40+00:00", "date_modified": "2025-08-06T12:41:04+00:00"}, {"id": "https://www.denverpost.com/2025/08/06/colorado-wolf-death-wyoming/", "url": "https://www.denverpost.com/2025/08/06/colorado-wolf-death-wyoming/", "title": "Collared Colorado wolf found dead in Wyoming", "date_published": "2025-08-06T17:56:50+00:00", "date_modified": "2025-08-06T13:02:49+00:00"}, {"id": "https://www.denverpost.com/2025/08/06/colorado-mesa-county-deputy-lawsuit-ice/", "url": "https://www.denverpost.com/2025/08/06/colorado-mesa-county-deputy-lawsuit-ice/", "title": "Mesa County to countersue Gov. Polis, AG Phil Weiser over deputy\u2019s alleged exchange with ICE", "date_published": "2025-08-06T16:55:56+00:00", "date_modified": "2025-08-06T11:27:43+00:00"}, {"id": "https://www.denverpost.com/2025/08/06/glenn-eric-thomas-colorado-springs/", "url": "https://www.denverpost.com/2025/08/06/glenn-eric-thomas-colorado-springs/", "title": "Charges dropped against Colorado Springs police sergeant accused of victim intimidation", "date_published": "2025-08-06T14:59:06+00:00", "date_modified": "2025-08-06T08:58:46+00:00"}, {"id": "https://www.denverpost.com/2025/08/06/colorado-special-session-trump-tax-bill/", "url": "https://www.denverpost.com/2025/08/06/colorado-special-session-trump-tax-bill/", "title": "Gov. Jared Polis calls Colorado lawmakers back for special session to deal with budget fallout from tax bill", "date_published": "2025-08-06T13:44:03+00:00", "date_modified": "2025-08-06T10:25:15+00:00"}]}