{"version": "https://jsonfeed.org/version/1.1", "title": "Denverite: Denver News", "home_page_url": "https://sreynen.github.io/denver-news/", "feed_url": "https://sreynen.github.io/denver-news/denverite.json", "items": [{"id": "https://www.denverpost.com/2022/04/17/sunday-wildfire-update-duck-pond-37e-evacuations/", "url": "https://www.denverpost.com/2022/04/17/sunday-wildfire-update-duck-pond-37e-evacuations/", "title": "Sunday wildfire updates: Evacuations continue in Eagle County; wind, dry weather expected Sunday", "date_published": "2022-04-17T16:15:06+00:00", "date_modified": "2022-04-17T10:21:44+00:00"}, {"id": "https://www.denverpost.com/2022/04/17/colorado-rural-counties-covid-aid-money/", "url": "https://www.denverpost.com/2022/04/17/colorado-rural-counties-covid-aid-money/", "title": "The Big Payout: In Colorado\u2019s sparsely populated counties, federal COVID aid was used, but often with suspicion", "date_published": "2022-04-17T12:00:15+00:00", "date_modified": "2022-04-16T14:56:46+00:00"}, {"id": "https://www.denverpost.com/2022/04/17/post-premium-top-stories-for-the-week-of-april-11-17/", "url": "https://www.denverpost.com/2022/04/17/post-premium-top-stories-for-the-week-of-april-11-17/", "title": "Post Premium: Top stories for the week of April 11-17", "date_published": "2022-04-17T12:00:14+00:00", "date_modified": "2022-04-16T16:19:32+00:00"}, {"id": "https://www.denverpost.com/2022/04/17/colorado-alcohol-deaths-pandemic/", "url": "https://www.denverpost.com/2022/04/17/colorado-alcohol-deaths-pandemic/", "title": "Alcohol deaths jumped by nearly 30% in Colorado in 2020 with less treatment, more drinking alone", "date_published": "2022-04-17T12:00:05+00:00", "date_modified": "2022-04-15T16:03:35+00:00"}, {"id": "https://www.denverpost.com/2022/04/17/jay-norvell-inside-csu-rams-football-2022/", "url": "https://www.denverpost.com/2022/04/17/jay-norvell-inside-csu-rams-football-2022/", "title": "A day inside CSU Rams football: For coach Jay Norvell, no detail is too small. No person, either.", "date_published": "2022-04-17T11:45:57+00:00", "date_modified": "2022-04-16T16:43:59+00:00"}, {"id": "https://www.denverpost.com/2022/04/16/wildfire-i-70-glenwood-canyon-gypsum/", "url": "https://www.denverpost.com/2022/04/16/wildfire-i-70-glenwood-canyon-gypsum/", "title": "Wildfire along I-70 shuts down roadway between Glenwood Springs and Gypsum", "date_published": "2022-04-16T23:21:03+00:00", "date_modified": "2022-04-16T17:27:21+00:00"}, {"id": "https://www.denverpost.com/2022/04/16/denver-free-fentanyl-test-strips-narcan-demand/", "url": "https://www.denverpost.com/2022/04/16/denver-free-fentanyl-test-strips-narcan-demand/", "title": "Denver offered free drug test strips and Narcan. Demand was overwhelming.", "date_published": "2022-04-16T22:23:23+00:00", "date_modified": "2022-04-16T16:28:58+00:00"}, {"id": "https://www.denverpost.com/2022/04/16/magic-mushrooms-for-therapy-vets-help-sway-conservatives/", "url": "https://www.denverpost.com/2022/04/16/magic-mushrooms-for-therapy-vets-help-sway-conservatives/", "title": "\u201cMagic mushrooms\u201d for therapy? Vets help sway conservatives", "date_published": "2022-04-16T21:16:16+00:00", "date_modified": "2022-04-16T15:28:11+00:00"}, {"id": "https://www.denverpost.com/2022/04/16/wildfire-larimer-county-37e-update/", "url": "https://www.denverpost.com/2022/04/16/wildfire-larimer-county-37e-update/", "title": "Wildfire in Larimer County has burned over 100 acres, no structures lost", "date_published": "2022-04-16T17:22:59+00:00", "date_modified": "2022-04-16T11:22:59+00:00"}, {"id": "https://www.denverpost.com/2022/04/16/denver-weather-fire-weather-watch/", "url": "https://www.denverpost.com/2022/04/16/denver-weather-fire-weather-watch/", "title": "Denver weather: Fire Weather Watch is posted for widespread areas on Sunday", "date_published": "2022-04-16T17:03:45+00:00", "date_modified": "2022-04-16T11:03:45+00:00"}, {"id": "https://www.denverpost.com/2022/04/16/denver-first-time-homebuyers/", "url": "https://www.denverpost.com/2022/04/16/denver-first-time-homebuyers/", "title": "Realty reality check: The ins, outs and ughs of first-time homebuying in Denver", "date_published": "2022-04-16T12:00:48+00:00", "date_modified": "2022-04-15T20:26:34+00:00"}, {"id": "https://www.denverpost.com/2022/04/16/how-to-help-ukraine/", "url": "https://www.denverpost.com/2022/04/16/how-to-help-ukraine/", "title": "\u201cThese are my people\u201d: How Coloradans are helping get vital aid to Ukraine \u2014 and planning longer-term support", "date_published": "2022-04-16T12:00:30+00:00", "date_modified": "2022-04-15T20:26:08+00:00"}, {"id": "https://www.denverpost.com/2022/04/15/ryan-lee-martin-lakewood-arsons/", "url": "https://www.denverpost.com/2022/04/15/ryan-lee-martin-lakewood-arsons/", "title": "Golden man who allegedly started a $2 million construction fire is arrested", "date_published": "2022-04-16T02:16:05+00:00", "date_modified": "2022-04-15T20:16:05+00:00"}, {"id": "https://www.denverpost.com/2022/04/15/davita-trial-jury-verdict/", "url": "https://www.denverpost.com/2022/04/15/davita-trial-jury-verdict/", "title": "Jury acquits DaVita, ex-CEO Kent Thiry on all counts in landmark antitrust trial", "date_published": "2022-04-15T22:19:06+00:00", "date_modified": "2022-04-15T16:19:06+00:00"}, {"id": "https://www.denverpost.com/2022/04/15/denver-fire-granville-townhomes/", "url": "https://www.denverpost.com/2022/04/15/denver-fire-granville-townhomes/", "title": "One person suffers smoke inhalation in Denver townhome fire on Friday", "date_published": "2022-04-15T20:59:11+00:00", "date_modified": "2022-04-15T14:59:11+00:00"}, {"id": "https://www.denverpost.com/2022/04/15/boulder-king-soopers-shooting-suspect-incompetent/", "url": "https://www.denverpost.com/2022/04/15/boulder-king-soopers-shooting-suspect-incompetent/", "title": "Boulder King Soopers suspect still incompetent to stand trial, judge says", "date_published": "2022-04-15T20:13:33+00:00", "date_modified": "2022-04-15T14:13:33+00:00"}, {"id": "https://www.denverpost.com/2022/04/15/levelle-desean-brownlow-denver-shooting-death-arrest/", "url": "https://www.denverpost.com/2022/04/15/levelle-desean-brownlow-denver-shooting-death-arrest/", "title": "Suspect in Denver shooting death is arrested in Tennessee", "date_published": "2022-04-15T19:35:52+00:00", "date_modified": "2022-04-15T13:35:52+00:00"}, {"id": "https://www.denverpost.com/2022/04/15/angel-rodriguez-jefferson-county-homicide/", "url": "https://www.denverpost.com/2022/04/15/angel-rodriguez-jefferson-county-homicide/", "title": "Suspect arrested in homicide investigation of body found inside Jefferson County home", "date_published": "2022-04-15T18:43:14+00:00", "date_modified": "2022-04-15T12:44:08+00:00"}, {"id": "https://www.denverpost.com/2022/04/15/denver-center-theatre-co-2022-23-season-lineup-shows-theater-of-the-mind-david-byrne/", "url": "https://www.denverpost.com/2022/04/15/denver-center-theatre-co-2022-23-season-lineup-shows-theater-of-the-mind-david-byrne/", "title": "Denver Center Theatre Co.\u2019s 2022-23 shows: David Byrne\u2019s \u201cTheater of the Mind,\u201d Camp Christmas and more", "date_published": "2022-04-15T18:36:36+00:00", "date_modified": "2022-04-15T12:36:36+00:00"}, {"id": "https://www.denverpost.com/2022/04/15/south-carolina-inmate-picks-firing-squad-over-electric-chair/", "url": "https://www.denverpost.com/2022/04/15/south-carolina-inmate-picks-firing-squad-over-electric-chair/", "title": "South Carolina inmate picks firing squad over electric chair", "date_published": "2022-04-15T18:23:37+00:00", "date_modified": "2022-04-15T13:03:54+00:00"}, {"id": "https://www.denverpost.com/2022/04/15/its-not-over-covid-19-cases-are-on-the-rise-again-in-us/", "url": "https://www.denverpost.com/2022/04/15/its-not-over-covid-19-cases-are-on-the-rise-again-in-us/", "title": "It\u2019s not over: COVID-19 cases are on the rise again in U.S.", "date_published": "2022-04-15T18:22:45+00:00", "date_modified": "2022-04-15T12:33:40+00:00"}, {"id": "https://www.denverpost.com/2022/04/15/russell-wilson-ciara-colorado-childrens-hospital/", "url": "https://www.denverpost.com/2022/04/15/russell-wilson-ciara-colorado-childrens-hospital/", "title": "Where Russell Wilson and Ciara have been spotted in Denver so far", "date_published": "2022-04-15T17:32:34+00:00", "date_modified": "2022-04-15T11:32:34+00:00"}, {"id": "https://www.denverpost.com/2022/04/15/colorado-anti-doxxing-law-teachers/", "url": "https://www.denverpost.com/2022/04/15/colorado-anti-doxxing-law-teachers/", "title": "Colorado\u2019s growing anti-doxxing law could soon include teachers", "date_published": "2022-04-15T16:08:55+00:00", "date_modified": "2022-04-15T10:08:55+00:00"}, {"id": "https://www.denverpost.com/2022/04/15/colorado-family-lockdown-shanghai/", "url": "https://www.denverpost.com/2022/04/15/colorado-family-lockdown-shanghai/", "title": "Colorado family trapped in Shanghai\u2019s \u201czero COVID\u201d lockdown", "date_published": "2022-04-15T16:06:41+00:00", "date_modified": "2022-04-15T10:13:30+00:00"}, {"id": "https://www.denverpost.com/2022/04/15/denver-weather-friday-weekend-sunny-warm/", "url": "https://www.denverpost.com/2022/04/15/denver-weather-friday-weekend-sunny-warm/", "title": "Denver weather: Breezy, warm and sunny weekend ahead", "date_published": "2022-04-15T12:42:30+00:00", "date_modified": "2022-04-15T06:42:30+00:00"}, {"id": "https://www.denverpost.com/2022/04/15/colorado-covid-aid-money-health-care-hospitals/", "url": "https://www.denverpost.com/2022/04/15/colorado-covid-aid-money-health-care-hospitals/", "title": "The Big Payout: Colorado health care providers used COVID aid as lifelines to stay afloat", "date_published": "2022-04-15T12:00:43+00:00", "date_modified": "2022-04-14T17:18:34+00:00"}, {"id": "https://www.denverpost.com/2022/04/15/jefferson-county-library-no-staff-automation/", "url": "https://www.denverpost.com/2022/04/15/jefferson-county-library-no-staff-automation/", "title": "A ghost library opens in Jefferson County. It might be the first one like it in the country.", "date_published": "2022-04-15T12:00:43+00:00", "date_modified": "2022-04-15T06:08:00+00:00"}, {"id": "https://www.denverpost.com/2022/04/15/flyin-west-john-hand-theater-review-denver/", "url": "https://www.denverpost.com/2022/04/15/flyin-west-john-hand-theater-review-denver/", "title": "Review: In \u201cFlyin\u2019 West,\u201d four Black women hold fast to their chunk of Kansas prairie", "date_published": "2022-04-15T12:00:13+00:00", "date_modified": "2022-04-14T12:50:24+00:00"}, {"id": "https://www.denverpost.com/2022/04/15/biggest-denver-summer-concerts-2022-weeknd-imagine-dragons-shawn-mendes/", "url": "https://www.denverpost.com/2022/04/15/biggest-denver-summer-concerts-2022-weeknd-imagine-dragons-shawn-mendes/", "title": "10 of the biggest, best Denver concerts of 2022: The Weeknd, Imagine Dragons, Shawn Mendes and more", "date_published": "2022-04-15T12:00:12+00:00", "date_modified": "2022-04-14T12:56:42+00:00"}, {"id": "https://www.denverpost.com/2022/04/15/colorado-supreme-court-justices-testify-reform-bill-judicial-discipline/", "url": "https://www.denverpost.com/2022/04/15/colorado-supreme-court-justices-testify-reform-bill-judicial-discipline/", "title": "Colorado\u2019s chief justice acknowledges \u201cinadequacies\u201d in state\u2019s system for disciplining judges", "date_published": "2022-04-15T12:00:10+00:00", "date_modified": "2022-04-15T06:08:18+00:00"}]}